README.md
setup.py
naegin/__init__.py
naegin/errors.py
naegin/image.py
naegin/wrapper.py
naegin.egg-info/PKG-INFO
naegin.egg-info/SOURCES.txt
naegin.egg-info/dependency_links.txt
naegin.egg-info/requires.txt
naegin.egg-info/top_level.txt