Metadata-Version: 1.1
Name: naegin
Version: 1.0.3
Summary: API Wrapper em Python para Naegin
Home-page: https://github.com/Naegin/naegin
Author: Naegin
Author-email: UNKNOWN
License: MIT License
Keywords: naegin,api,wrapper,images,pt-br,brazilian,portuguese
Platform: UNKNOWN
Classifier: Intended Audience :: Developers
Classifier: License :: OSI Approved :: MIT License
Classifier: Operating System :: OS Independent
Classifier: Natural Language :: Portuguese (Brazilian)
Classifier: Programming Language :: Python :: 3.6
Classifier: Programming Language :: Python :: 3.7
Classifier: Topic :: Internet
Classifier: Topic :: Utilities
Classifier: Topic :: Software Development :: Libraries :: Python Modules
